{
  "scripts" : [
    {
      "type" : "box_collider",
      "name" : "aabb_collider.057",
      "args" : {
        "position" : {
          "x" : -0.0,
          "y" : -4.9073262214660645,
          "z" : 26.45863151550293
        },
        "rotation" : {
          "x" : -0.0,
          "y" : 0.0,
          "z" : 0.0
        },
        "size" : {
          "x" : 1.0,
          "y" : 2.1626131534576416,
          "z" : 22.963523864746094
        }
      }
    },
    {
      "type" : "plane_collider",
      "name" : "plane_collider.036",
      "args" : {
        "position" : {
          "x" : -3.062453269958496,
          "y" : -4.4755072593688965,
          "z" : 18.999366760253906
        },
        "rotation" : {
          "x" : -0.0,
          "y" : 0.0,
          "z" : -1.5707963705062866
        },
        "size" : {
          "x" : 14.995248794555664,
          "y" : 1.0,
          "z" : 37.93973922729492
        }
      }
    },
    {
      "type" : "plane_collider",
      "name" : "plane_collider.038",
      "args" : {
        "position" : {
          "x" : -0.0,
          "y" : 3.0,
          "z" : 5.245841979980469
        },
        "rotation" : {
          "x" : -3.1415927410125732,
          "y" : 0.0,
          "z" : 0.0
        },
        "size" : {
          "x" : 6.108293533325195,
          "y" : 1.0,
          "z" : 10.542271614074707
        }
      }
    },
    {
      "type" : "model",
      "name" : "model.032",
      "args" : {
        "position" : {
          "x" : -0.0,
          "y" : 0.0,
          "z" : 0.0
        },
        "rotation" : {
          "x" : -0.0,
          "y" : 0.0,
          "z" : 0.0
        },
        "size" : {
          "x" : 1.0,
          "y" : 1.0,
          "z" : 1.0
        },
        "mesh" : "../assets/models/procedural/seg5w.mesh",
        "normal" : "../assets/textures/Neutral_Normal.png",
        "diffuse" : "../assets/textures/backrooms/backrooms_wall_color.png",
        "height" : "../assets/textures/White_Square.png",
        "data" : "../assets/textures/default_data.png"
      }
    },
    {
      "type" : "model",
      "name" : "model.033",
      "args" : {
        "position" : {
          "x" : -0.0,
          "y" : 0.0,
          "z" : 0.0
        },
        "rotation" : {
          "x" : -0.0,
          "y" : 0.0,
          "z" : 0.0
        },
        "size" : {
          "x" : 1.0,
          "y" : 1.0,
          "z" : 1.0
        },
        "mesh" : "../assets/models/procedural/seg5f.mesh",
        "normal" : "../assets/textures/backrooms/carpet_normal.png",
        "diffuse" : "../assets/textures/backrooms/carpet_color.png",
        "height" : "../assets/textures/backrooms/carpet_height.png",
        "data" : "../assets/textures/backrooms/carpet_data.png"
      }
    },
    {
      "type" : "model",
      "name" : "model.034",
      "args" : {
        "position" : {
          "x" : -0.0,
          "y" : 0.0,
          "z" : 0.0
        },
        "rotation" : {
          "x" : -0.0,
          "y" : 0.0,
          "z" : 0.0
        },
        "size" : {
          "x" : 1.0,
          "y" : 1.0,
          "z" : 1.0
        },
        "mesh" : "../assets/models/procedural/seg5c.mesh",
        "normal" : "../assets/textures/backrooms/ceiling_normal.png",
        "diffuse" : "../assets/textures/backrooms/ceiling_color.png",
        "height" : "../assets/textures/backrooms/ceiling_height.png",
        "data" : "../assets/textures/backrooms/ceiling_data.png"
      }
    },
    {
      "type" : "segment_gate",
      "name" : "segment_gate.008",
      "args" : {
        "position" : {
          "x" : -0.0,
          "y" : -9.0,
          "z" : 38.0
        },
        "rotation" : {
          "x" : -1.5707963705062866,
          "y" : 0.0,
          "z" : 1.5707963705062866
        },
        "size" : {
          "x" : 6.000000953674316,
          "y" : 1.0,
          "z" : 5.999999523162842
        }
      }
    },
    {
      "type" : "box_collider",
      "name" : "aabb_collider.064",
      "args" : {
        "position" : {
          "x" : -0.0,
          "y" : -3.9181771278381348,
          "z" : 3.47642183303833
        },
        "rotation" : {
          "x" : -0.0,
          "y" : 0.0,
          "z" : 0.0
        },
        "size" : {
          "x" : 6.058157444000244,
          "y" : 1.8400354385375977,
          "z" : 6.99151086807251
        }
      }
    },
    {
      "type" : "box_collider",
      "name" : "aabb_collider.065",
      "args" : {
        "position" : {
          "x" : 5.768662830133841e-16,
          "y" : -8.105924606323242,
          "z" : 8.771307945251465
        },
        "rotation" : {
          "x" : 1.0670827627182007,
          "y" : 1.1486784527793998e-16,
          "z" : -1.9446579449758253e-16
        },
        "size" : {
          "x" : 6.058157444000244,
          "y" : 1.84003484249115,
          "z" : 10.72990608215332
        }
      }
    },
    {
      "type" : "plane_collider",
      "name" : "plane_collider.031",
      "args" : {
        "position" : {
          "x" : -3.3346984096055583e-15,
          "y" : -12.018146514892578,
          "z" : 24.78057098388672
        },
        "rotation" : {
          "x" : -0.0,
          "y" : 0.0,
          "z" : 0.0
        },
        "size" : {
          "x" : 6.108293533325195,
          "y" : 1.0,
          "z" : 26.41521644592285
        }
      }
    },
    {
      "type" : "plane_collider",
      "name" : "plane_collider.037",
      "args" : {
        "position" : {
          "x" : 3.0624499320983887,
          "y" : -4.4755072593688965,
          "z" : 18.999366760253906
        },
        "rotation" : {
          "x" : -0.0,
          "y" : 0.0,
          "z" : 1.5707963705062866
        },
        "size" : {
          "x" : 14.995248794555664,
          "y" : 1.0,
          "z" : 37.93973922729492
        }
      }
    },
    {
      "type" : "box_collider",
      "name" : "aabb_collider.066",
      "args" : {
        "position" : {
          "x" : -1.032632053799584e-15,
          "y" : -0.8573884963989258,
          "z" : 13.218669891357422
        },
        "rotation" : {
          "x" : 1.0670827627182007,
          "y" : 1.1486784527793998e-16,
          "z" : -1.9446579449758253e-16
        },
        "size" : {
          "x" : 6.058157444000244,
          "y" : 1.84003484249115,
          "z" : 10.72990608215332
        }
      }
    }
  ]
}